reverse/__init__.py
reverse/reverse.py
Hnatyshakten-1.0.0.dist-info/METADATA
Hnatyshakten-1.0.0.dist-info/WHEEL
Hnatyshakten-1.0.0.dist-info/top_level.txt
Hnatyshakten-1.0.0.dist-info/RECORD
